{
    "main":
    {
        "display":"flex",
        "flexDirection":"column",
        "backgroundColor":"black"
    },
    "ab":
    {
        "display":"flex",
        "flexDirection":"row",
        "maxHeight":"550px"
    },
    "a_1":
    {
        "display":"flex",
        "flexDirection":"column",
        "width":"1100px",
        "padding":10
    },
    "a_2":
    {
        "display":"flex",
        "flexDirection":"column",
        "width":"300px",
        "padding":10
    },
    "b_12":
    {
        "display":"flex",
        "flexDirection":"column",
        "width":"700px",
        "padding":10
    },
    "b_2_2":
    {
        "display":"flex",
        "flexDirection":"row",
        "maxWidth":"700px",
        "padding":0,
        "overflowX":"scroll"
    }
}